Metadata-Version: 2.4
Name: burnysc2
Version: 7.1.3
Summary: A StarCraft II API Client for Python 3
Author-email: BurnySc2 <gamingburny@gmail.com>
Project-URL: Repository, https://github.com/Burnysc2/python-sc2
Project-URL: Documentation, https://burnysc2.github.io/python-sc2
Keywords: StarCraft,StarCraft 2,StarCraft II,AI,Bot
Classifier: Intended Audience :: Developers
Classifier: Intended Audience :: Education
Classifier: Intended Audience :: Science/Research
Classifier: Topic :: Games/Entertainment
Classifier: Topic :: Games/Entertainment :: Real Time Strategy
Classifier: Topic :: Scientific/Engineering
Classifier: Topic :: Scientific/Engineering :: Artificial Intelligence
Classifier: Operating System :: POSIX :: Linux
Classifier: Operating System :: Microsoft :: Windows
Classifier: Operating System :: MacOS :: MacOS X
Classifier: Programming Language :: Python :: 3
Classifier: Programming Language :: Python :: 3.9
Classifier: Programming Language :: Python :: 3.10
Classifier: Programming Language :: Python :: 3.11
Classifier: Programming Language :: Python :: 3.12
Classifier: Programming Language :: Python :: 3.13
Classifier: Programming Language :: Python :: 3.14
Requires-Python: <3.15,>=3.9
License-File: LICENSE
Requires-Dist: aiohttp>=3.11.10
Requires-Dist: loguru>=0.7.3
Requires-Dist: mpyq>=0.2.5
Requires-Dist: numpy>=2.3.3; python_full_version >= "3.14"
Requires-Dist: numpy>=2.1.0; python_full_version >= "3.13"
Requires-Dist: numpy>=2.0.0; python_full_version < "3.13"
Requires-Dist: portpicker>=1.6.0
Requires-Dist: protobuf<4.0.0
Requires-Dist: s2clientprotocol>=5.0.14.93333.0
Requires-Dist: scipy>=1.16.3; python_full_version >= "3.14"
Requires-Dist: scipy>=1.14.1; python_full_version >= "3.13"
Requires-Dist: scipy>=1.7.1; python_full_version < "3.13"
Dynamic: license-file
